keyboard/__init__.py
keyboard/__main__.py
keyboard/cli.py
keyboard/keyboard.py
rlane_keyboard-1.0.2.dist-info/METADATA
rlane_keyboard-1.0.2.dist-info/WHEEL
rlane_keyboard-1.0.2.dist-info/entry_points.txt
rlane_keyboard-1.0.2.dist-info/licenses/LICENSE
rlane_keyboard-1.0.2.dist-info/RECORD
