Metadata-Version: 2.1
Name: rlane-keyboard
Version: 1.0.2
Summary: computer keyboard model
Keywords: keyboard,shortcuts
Author-Email: Russel Lane <russel@rlane.com>
License: MIT
Classifier: Development Status :: 4 - Beta
Classifier: Intended Audience :: Developers
Classifier: License :: OSI Approved :: MIT License
Classifier: Programming Language :: Python :: 3
Classifier: Topic :: Software Development :: Libraries :: Python Modules
Project-URL: Homepage, https://github.com/russellane/keyboard
Requires-Python: >=3.10
Requires-Dist: rlane-libcli>=1.0.8
